wallo/__init__.py
wallo/busyDialog.py
wallo/configFileManager.py
wallo/configMain.py
wallo/configTabPrompts.py
wallo/configTabServices.py
wallo/configTabString.py
wallo/docxExport.py
wallo/editor.py
wallo/llmProcessor.py
wallo/main.py
wallo/pdfDocumentProcessor.py
wallo/worker.py
wallo-0.2.0.dist-info/licenses/LICENSE
wallo-0.2.0.dist-info/METADATA
wallo-0.2.0.dist-info/WHEEL
wallo-0.2.0.dist-info/top_level.txt
wallo-0.2.0.dist-info/RECORD
