Metadata-Version: 2.4
Name: wallo
Version: 0.2.0
Summary: WALLO - Writing Assistant leveraging Large Language mOdels
Author-email: Steffen <sbrinckm@gmail.com>
Requires-Python: >=3.10
License-File: LICENSE
Requires-Dist: PySide6
Requires-Dist: qtawesome
Requires-Dist: openai
Requires-Dist: pypandoc
Requires-Dist: pdfplumber
Provides-Extra: dev
Requires-Dist: pylint; extra == "dev"
Requires-Dist: mypy; extra == "dev"
Dynamic: license-file
